{"Year":{"0":2010,"1":2011,"2":2012,"3":2013,"4":2014,"5":2015,"6":2016,"7":2017,"8":2018,"9":2019,"10":2020},"Job Title":{"0":"Configuration Management Specialist","1":"Configuration Management Specialist","2":"Configuration Management Specialist","3":"Configuration Management Specialist","4":"Configuration Management Specialist","5":"Configuration Management Specialist","6":"Configuration Management Specialist","7":"Configuration Management Specialist","8":"Configuration Management Specialist","9":"Configuration Management Specialist","10":"Configuration Management Specialist"},"Table":{"0":null,"1":null,"2":null,"3":null,"4":null,"5":{"EMPLOYER":{"0":"USM BUSINESS SYSTEMS INC","1":"USM BUSINESS SYSTEMS INC"},"JOB TITLE":{"0":"CONFIGURATION MANAGEMENT SPECIALIST","1":"CONFIGURATION MANAGEMENT SPECIALIST"},"BASE SALARY":{"0":"84,740","1":"84,740"},"LOCATION":{"0":"SEATTLE, WA","1":"SEATTLE, WA"},"SUBMIT DATE":{"0":"07\/31\/2015","1":"08\/11\/2015"},"START DATE":{"0":"07\/31\/2015","1":"08\/11\/2015"}},"6":null,"7":{"EMPLOYER":{"0":"USM BUSINESS SYSTEMS INC"},"JOB TITLE":{"0":"CONFIGURATION MANAGEMENT SPECIALIST"},"BASE SALARY":{"0":"80,000"},"LOCATION":{"0":"COLUMBIA, MD"},"SUBMIT DATE":{"0":"08\/25\/2017"},"START DATE":{"0":"08\/28\/2017"}},"8":{"EMPLOYER":{"0":"DIGITAL MANAGEMENT LLC","1":"CROWD SOFTWARE CONSULTING LLC"},"JOB TITLE":{"0":"CONFIGURATION MANAGEMENT SPECIALIST","1":"CONFIGURATION MANAGEMENT SPECIALIST"},"BASE SALARY":{"0":"75,000","1":"90,189"},"LOCATION":{"0":"CHANTILLY, VA","1":"FORT WORTH, TX"},"SUBMIT DATE":{"0":"03\/08\/2018","1":"05\/02\/2018"},"START DATE":{"0":"09\/07\/2018","1":"05\/09\/2018"}},"9":{"EMPLOYER":{"0":"USM BUSINESS SYSTEMS INC"},"JOB TITLE":{"0":"CONFIGURATION MANAGEMENT SPECIALIST"},"BASE SALARY":{"0":"82,000"},"LOCATION":{"0":"COLUMBIA, MD"},"SUBMIT DATE":{"0":"05\/15\/2019"},"START DATE":{"0":"10\/21\/2019"}},"10":{"EMPLOYER":{"0":"HARMONIA HOLDINGS GROUP LLC","1":"CLIENT NETWORK SERVICES LLC","2":"ARTISAN VEHICLE SYSTEMS INC"},"JOB TITLE":{"0":"CONFIGURATION MANAGEMENT SPECIALIST","1":"CONFIGURATION MANAGEMENT SPECIALIST","2":"CONFIGURATION MANAGEMENT SPECIALIST"},"BASE SALARY":{"0":"78,041","1":"92,378","2":"105,000"},"LOCATION":{"0":"MCLEAN, VA","1":"ROCKVILLE, MD","2":"CAMARILLO, CA"},"SUBMIT DATE":{"0":"04\/14\/2020","1":"04\/21\/2020","2":"03\/13\/2020"},"START DATE":{"0":"09\/05\/2020","1":"08\/24\/2020","2":"09\/12\/2020"}}}}