{"Year":{"0":2010,"1":2011,"2":2012,"3":2013,"4":2014,"5":2015,"6":2016,"7":2017,"8":2018,"9":2019,"10":2020},"Job Title":{"0":"SAP Basis Administrator","1":"SAP Basis Administrator","2":"SAP Basis Administrator","3":"SAP Basis Administrator","4":"SAP Basis Administrator","5":"SAP Basis Administrator","6":"SAP Basis Administrator","7":"SAP Basis Administrator","8":"SAP Basis Administrator","9":"SAP Basis Administrator","10":"SAP Basis Administrator"},"Table":{"0":null,"1":null,"2":null,"3":null,"4":{"EMPLOYER":{"0":"DSYS INC","1":"MOLEX INCORPORATED","2":"MOLEX INCORPORATED","3":"EVANTAGE SOLUTIONS INC","4":"ERP ANALYSTS INC","5":"AMPLE IT SERVICES LLC","6":"AMPLE IT SERVICES LLC","7":"TALENTED IT INC","8":"THE CHAMBERLAIN GROUP INC","9":"TALENTED IT INC","10":" Ezoic - mid_content - mid_content ","11":"SCHRILL TECHNOLOGIES INC","12":"ST JUDE MEDICAL INC","13":"EATON CORPORATION","14":"MEAD JOHNSON & COMPANY LLC","15":"ZULILY INC","16":"TATE & LYLE AMERICAS LLC"},"JOB TITLE":{"0":"SAP BASIS ADMINISTRATOR","1":"SAP BASIS ADMINISTRATOR","2":"SAP BASIS ADMINISTRATOR","3":"SAP BASIS ADMINISTRATOR","4":"SAP BASIS ADMINISTRATOR","5":"SAP BASIS ADMINISTRATOR","6":"SAP BASIS ADMINISTRATOR","7":"SAP BASIS ADMINISTRATOR","8":"SAP BASIS ADMINISTRATOR","9":"SAP BASIS ADMINISTRATOR","10":null,"11":"SAP BASIS ADMINISTRATOR","12":"SAP BASIS ADMINISTRATOR","13":"SAP BASIS ADMINISTRATOR","14":"SAP BASIS ADMINISTRATOR","15":"SAP BASIS ADMINISTRATOR","16":"SAP BASIS ADMINISTRATOR"},"BASE SALARY":{"0":"60,000","1":"66,976","2":"66,976","3":"74,963","4":"80,000","5":"80,000","6":"80,000","7":"80,000","8":"88,394","9":"90,000","10":null,"11":"90,000","12":"103,000","13":"104,437","14":"105,000","15":"110,000","16":"110,000"},"LOCATION":{"0":"SAVANNAH, GA","1":"LISLE, IL","2":"LISLE, IL","3":"HOUSTON, TX","4":"ST. LOUIS, MO","5":"ISSAQUAH, WA","6":"ISSAQUAH, WA","7":"NEWTON SQUARE, PA","8":"TUCSON, AZ","9":"NEWTON SQUARE, PA","10":null,"11":"HOUSTON, TX","12":"MINNETONKA, MN","13":"PEACHTREE CITY, GA","14":"EVANSVILLE, IN","15":"SEATTLE, WA","16":"HOFFMAN ESTATES, IL"},"SUBMIT DATE":{"0":"10\/17\/2014","1":"12\/10\/2014","2":"12\/10\/2014","3":"10\/02\/2014","4":"11\/14\/2014","5":"12\/08\/2014","6":"12\/09\/2014","7":"12\/31\/2014","8":"10\/01\/2014","9":"12\/31\/2014","10":null,"11":"10\/10\/2014","12":"10\/01\/2014","13":"10\/07\/2014","14":"12\/31\/2014","15":"12\/02\/2014","16":"12\/19\/2014"},"START DATE":{"0":"10\/20\/2014","1":"01\/12\/2015","2":"01\/12\/2015","3":"01\/01\/2015","4":"11\/20\/2014","5":"01\/01\/2015","6":"01\/01\/2015","7":"01\/12\/2015","8":"01\/01\/2015","9":"01\/12\/2015","10":null,"11":"10\/27\/2014","12":"10\/09\/2014","13":"03\/11\/2015","14":"01\/12\/2015","15":"12\/10\/2014","16":"04\/20\/2015"}},"5":{"EMPLOYER":{"0":"PROFESSIONAL SUPPORT INC","1":"I DREAM SYSTEMS INC","2":"MEAD JOHNSON & COMPANY LLC","3":"IT TRAILBLAZERS LLC","4":"IT TRAILBLAZERS LLC","5":"CYMA SYSTEMS INC","6":"TEK LEADERS INC","7":"EXPRESS GLOBAL SOLUTIONS LLC","8":"COMP CONSULTS INC","9":"AKT LLC","10":" Ezoic - mid_content - mid_content ","11":"CYMA SYSTEMS INC","12":"INNOVATIVE CONSULTING SOLUTIONS LLC","13":"TECH MATRIX INC","14":"MEAD JOHNSON & COMPANY LLC","15":"MEAD JOHNSON & COMPANY LLC","16":"INFINITY TECH GROUP INC","17":"EXPRESS GLOBAL SOLUTIONS LLC","18":"INTERACTIVE BUSINESS SERVICES INC","19":"DATALYSYS LLC","20":"VENSOFT SOLUTIONS INC","21":"VENSOFT SOLUTIONS INC","22":"VENSOFT SOLUTIONS INC","23":"DATALYSYS LLC","24":"KSOFT SYSTEMS INC","25":"QUANTUM INTEGRATORS GROUP LLC","26":"LOGICATECHINC","27":"VENNSYS LLC","28":"CDRP TECHNOLOGIES LLC","29":"MOLEX LLC","30":"ADVANCED TECHNOLOGY GROUP USA INC","31":"VALUE SOFTWARE PRODUCTS INC","32":"PYRAMID TECHNOLOGY SOLUTIONS INC","33":"MARK INFOTECH INC","34":"MARK INFOTECH INC","35":"CEDENT CONSULTING INC","36":"NPC INTERNATIONAL INC","37":"CEDENT CONSULTING INC","38":"ATLAS SYSTEMS INC","39":"ATLAS SYSTEMS INC","40":"\n","41":"CABELA'S INC","42":"PACCAR INC","43":"AMPLE IT SERVICES LLC","44":"ERP ANALYSTS INC","45":"AIR PRODUCTS AND CHEMICALS INC","46":"TAWA SUPERMARKET INC","47":"CONOCOPHILLIPS COMPANY","48":"COPART INC","49":"ENTEGRIS PROFESSIONAL SOLUTIONS INC","50":"PROLIM GLOBAL CORPORATION","51":"BJ'S WHOLESALE CLUB INC","52":"AMPLE IT SERVICES LLC","53":"MEDLINE INDUSTRIES INC","54":"99 CENTS ONLY STORES LLC","55":"99 CENTS ONLY STORES LLC","56":"BIO-RAD LABORATORIES INC","57":"AIG EMPLOYEE SERVICES INC","58":"PRIMESOURCE BUILDING PRODUCTS INC","59":"EATON","60":"LLOYDS & MARKER PROFESSIONAL SERVICES INC","61":"RESOURCE LOGISTICS INC","62":"NUSKIN ENTERPRISES","63":"GENERAL MOTORS COMPANY","64":"IQ SYSTEMS INC","65":"SAVVIS COMMUNICATIONS CORPORATION","66":"THE ANDERSONS INC","67":"BOB'S DISCOUNT FURNITURE LLC","68":"PALO ALTO NETWORKS INC"},"JOB TITLE":{"0":"SAP BASIS ADMINISTRATOR","1":"SAP BASIS ADMINISTRATOR","2":"SAP BASIS ADMINISTRATOR","3":"SAP BASIS ADMINISTRATOR","4":"SAP BASIS ADMINISTRATOR","5":"SAP BASIS ADMINISTRATOR","6":"SAP BASIS ADMINISTRATOR","7":"SAP BASIS ADMINISTRATOR","8":"SAP BASIS ADMINISTRATOR","9":"SAP BASIS ADMINISTRATOR","10":null,"11":"SAP BASIS ADMINISTRATOR","12":"SAP BASIS ADMINISTRATOR","13":"SAP BASIS ADMINISTRATOR","14":"SAP BASIS ADMINISTRATOR","15":"SAP BASIS ADMINISTRATOR","16":"SAP BASIS ADMINISTRATOR","17":"SAP BASIS ADMINISTRATOR","18":"SAP BASIS ADMINISTRATOR","19":"SAP BASIS ADMINISTRATOR","20":"SAP BASIS ADMINISTRATOR","21":"SAP BASIS ADMINISTRATOR","22":"SAP BASIS ADMINISTRATOR","23":"SAP BASIS ADMINISTRATOR","24":"SAP BASIS ADMINISTRATOR","25":"SAP BASIS ADMINISTRATOR","26":"SAP BASIS ADMINISTRATOR","27":"SAP BASIS ADMINISTRATOR","28":"SAP BASIS ADMINISTRATOR","29":"SAP BASIS ADMINISTRATOR","30":"SAP BASIS ADMINISTRATOR","31":"SAP BASIS ADMINISTRATOR","32":"SAP BASIS ADMINISTRATOR","33":"SAP BASIS ADMINISTRATOR","34":"SAP BASIS ADMINISTRATOR","35":"SAP BASIS ADMINISTRATOR","36":"SAP BASIS ADMINISTRATOR","37":"SAP BASIS ADMINISTRATOR","38":"SAP BASIS ADMINISTRATOR","39":"SAP BASIS ADMINISTRATOR","40":null,"41":"SAP BASIS ADMINISTRATOR","42":"SAP BASIS ADMINISTRATOR","43":"SAP BASIS ADMINISTRATOR","44":"SAP BASIS ADMINISTRATOR","45":"SAP BASIS ADMINISTRATOR","46":"SAP BASIS ADMINISTRATOR","47":"SAP BASIS ADMINISTRATOR","48":"SAP BASIS ADMINISTRATOR","49":"SAP BASIS ADMINISTRATOR","50":"SAP BASIS ADMINISTRATOR","51":"SAP BASIS ADMINISTRATOR","52":"SAP BASIS ADMINISTRATOR","53":"SAP BASIS ADMINISTRATOR","54":"SAP BASIS ADMINISTRATOR","55":"SAP BASIS ADMINISTRATOR","56":"SAP BASIS ADMINISTRATOR","57":"SAP BASIS ADMINISTRATOR","58":"SAP BASIS ADMINISTRATOR","59":"SAP BASIS ADMINISTRATOR","60":"SAP BASIS ADMINISTRATOR","61":"SAP BASIS ADMINISTRATOR","62":"SAP BASIS ADMINISTRATOR","63":"SAP BASIS ADMINISTRATOR","64":"SAP BASIS ADMINISTRATOR","65":"SAP BASIS ADMINISTRATOR","66":"SAP BASIS ADMINISTRATOR","67":"SAP BASIS ADMINISTRATOR","68":"SAP BASIS ADMINISTRATOR"},"BASE SALARY":{"0":"120,000","1":"48,100","2":"50,898","3":"55,000","4":"55,000","5":"60,000","6":"60,000","7":"60,000","8":"60,000","9":"60,000","10":null,"11":"60,100","12":"60,133","13":"61,000","14":"62,026","15":"62,026","16":"62,442","17":"65,000","18":"65,000","19":"65,000","20":"65,000","21":"65,000","22":"65,000","23":"65,042","24":"66,000","25":"66,560","26":"67,000","27":"67,309","28":"68,000","29":"68,931","30":"69,347","31":"70,000","32":"70,117","33":"72,000","34":"72,000","35":"75,000","36":"75,000","37":"75,000","38":"75,000","39":"75,000","40":null,"41":"79,040","42":"79,200","43":"80,000","44":"80,000","45":"83,179","46":"90,147","47":"90,240","48":"94,400","49":"95,000","50":"95,000","51":"95,763","52":"100,000","53":"100,000","54":"105,000","55":"105,000","56":"106,891","57":"110,000","58":"110,406","59":"111,384","60":"115,000","61":"120,000","62":"120,081","63":"120,192","64":"123,264","65":"123,510","66":"125,000","67":"125,000","68":"135,000"},"LOCATION":{"0":"WILLIAMSVILLE, NY","1":"KATY, TX","2":"EVANSVILLE, IN","3":"MENOMONEE FALLS, WI","4":"MENOMONEE FALLS, WI","5":"BELLAIRE, TX","6":"BLOOMINGTON, MN","7":"PALO ALTO, CA","8":"HOUSTON, TX","9":"FORT WORTH, TX","10":null,"11":"BELLAIRE, TX","12":"PLANO, TX","13":"STAMFORD, CT","14":"EVANSVILLE, IN","15":"EVANSVILLE, IN","16":"SCOTCH PLAINS, NJ","17":"PALO ALTO, CA","18":"LAKEFOREST, IL","19":"DUBLIN, OH","20":"NEWARK, DE","21":"NEWARK, DE","22":"NEWARK, DE","23":"FRISCO, TX","24":"SAVANNAH, GA","25":"RARITAN, NJ","26":"MALTA, NY","27":"GOLDEN VALLEY, MN","28":"SANTA CLARITA, CA","29":"LISLE, IL","30":"NEWTOWN SQUARE, PA","31":"SANTA CLARA, CA","32":"COLUMBUS, IN","33":"EAST BRUNSWICK, NJ","34":"EAST BRUNSWICK, NJ","35":"RUMFORD, RI","36":"PITTSBURG, KS","37":"CHARLOTTE, NC","38":"PRINCETON, NJ","39":"PARSIPPANY, NJ","40":null,"41":"LINCOLN, NE","42":"RENTON, WA","43":"FRISCO, TX","44":"ST. LOUIS, MO","45":"ALLENTOWN, PA","46":"BUENA PARK, CA","47":"BARTLESVILLE, OK","48":"DALLAS, TX","49":"BILLERICA, MA","50":"PARSIPPANY, NJ","51":"WESTBOROUGH, MA","52":"HOUSTON, TX","53":"MUNDELEIN, IL","54":"KATY, TX","55":"KATY, TX","56":"HERCULES, CA","57":"PARSIPPANY, NJ","58":"IRVING, TX","59":"PEACHTREE CITY, GA","60":"ISSAQUAH, WA","61":"ATLANTA, GA","62":"PROVO, UT","63":"ROSWELL, GA","64":"WALTHAM, MA","65":"MOORESTOWN, NJ","66":"MAUMEE, OH","67":"MANCHESTER, CT","68":"SANTA CLARA, CA"},"SUBMIT DATE":{"0":"03\/06\/2015","1":"03\/07\/2015","2":"06\/17\/2015","3":"08\/27\/2015","4":"08\/27\/2015","5":"03\/20\/2015","6":"09\/25\/2015","7":"03\/09\/2015","8":"05\/12\/2015","9":"07\/10\/2015","10":null,"11":"03\/20\/2015","12":"09\/16\/2015","13":"12\/07\/2015","14":"04\/03\/2015","15":"02\/20\/2015","16":"03\/09\/2015","17":"03\/17\/2015","18":"03\/20\/2015","19":"12\/15\/2015","20":"05\/06\/2015","21":"07\/23\/2015","22":"09\/02\/2015","23":"12\/23\/2015","24":"04\/27\/2015","25":"02\/26\/2015","26":"10\/14\/2015","27":"01\/06\/2015","28":"03\/16\/2015","29":"12\/10\/2015","30":"02\/13\/2015","31":"08\/19\/2015","32":"08\/04\/2015","33":"06\/22\/2015","34":"06\/22\/2015","35":"10\/29\/2015","36":"12\/17\/2015","37":"04\/27\/2015","38":"01\/15\/2015","39":"08\/18\/2015","40":null,"41":"01\/30\/2015","42":"04\/29\/2015","43":"03\/13\/2015","44":"12\/18\/2015","45":"04\/01\/2015","46":"05\/15\/2015","47":"10\/15\/2015","48":"01\/09\/2015","49":"11\/20\/2015","50":"09\/23\/2015","51":"09\/17\/2015","52":"10\/21\/2015","53":"05\/05\/2015","54":"10\/01\/2015","55":"10\/01\/2015","56":"03\/09\/2015","57":"11\/12\/2015","58":"01\/30\/2015","59":"10\/23\/2015","60":"02\/11\/2015","61":"07\/24\/2015","62":"08\/10\/2015","63":"03\/19\/2015","64":"04\/28\/2015","65":"12\/23\/2015","66":"11\/10\/2015","67":"06\/29\/2015","68":"12\/28\/2015"},"START DATE":{"0":"09\/04\/2015","1":"09\/01\/2015","2":"07\/01\/2015","3":"09\/08\/2015","4":"09\/08\/2015","5":"09\/16\/2015","6":"10\/05\/2015","7":"09\/08\/2015","8":"05\/13\/2015","9":"10\/01\/2015","10":null,"11":"09\/16\/2015","12":"12\/31\/2015","13":"12\/14\/2015","14":"04\/10\/2015","15":"02\/26\/2015","16":"09\/08\/2015","17":"09\/16\/2015","18":"09\/19\/2015","19":"01\/05\/2016","20":"05\/06\/2015","21":"07\/23\/2015","22":"09\/02\/2015","23":"01\/05\/2016","24":"05\/01\/2015","25":"03\/04\/2015","26":"12\/25\/2015","27":"03\/26\/2015","28":"09\/01\/2015","29":"01\/11\/2016","30":"02\/13\/2015","31":"08\/19\/2015","32":"01\/28\/2016","33":"10\/02\/2015","34":"10\/01\/2015","35":"11\/09\/2015","36":"12\/28\/2015","37":"04\/27\/2015","38":"02\/01\/2015","39":"08\/19\/2015","40":null,"41":"07\/01\/2015","42":"10\/01\/2015","43":"03\/13\/2015","44":"05\/09\/2016","45":"04\/20\/2015","46":"11\/14\/2015","47":"11\/02\/2015","48":"02\/09\/2015","49":"11\/23\/2015","50":"12\/30\/2015","51":"11\/25\/2015","52":"10\/21\/2015","53":"10\/01\/2015","54":"11\/02\/2015","55":"11\/02\/2015","56":"03\/30\/2015","57":"11\/23\/2015","58":"07\/03\/2015","59":"11\/15\/2015","60":"02\/25\/2015","61":"08\/03\/2015","62":"02\/09\/2016","63":"09\/18\/2015","64":"09\/30\/2015","65":"12\/30\/2015","66":"12\/15\/2015","67":"07\/13\/2015","68":"12\/30\/2015"}},"6":{"EMPLOYER":{"0":"DEBAISE HOLDINGS LLC","1":"LOS ANGELES UNIFIED SCHOOL DISTRICT","2":"SCSK USA INC","3":"IT TRAILBLAZERS LLC","4":"IT TRAILBLAZERS LLC","5":"VIRTUE GROUP LLC","6":"ISITE TECHNOLOGIES INC","7":"VSLN INTERNATIONAL INC","8":"ADVANCED TECHNOLOGY GROUP USA INC","9":"YASH SOLUTIONS LLC","10":" Ezoic - mid_content - mid_content ","11":"TEKSKILLS INC","12":"INFINITY TECH GROUP INC","13":"INFINITY TECH GROUP INC","14":"ACCRETE SOLUTIONS LLC","15":"TACHYON TECHNOLOGIES LLC","16":"KSOFT SYSTEMS INC","17":"MANAGESERVE TECHNOLOGY INC","18":"AMPLE IT SERVICES LLC","19":"AGASTI LLC","20":"ISOLVERS INC","21":"ORBIS INC","22":"ORBIS INC","23":"JSMN INTERNATIONAL INC","24":"ERP GLOBAL INC","25":"RADIANT INFOSYS INC","26":"PROSOFT TECHNOLOGY GROUP INC","27":"SARGENTO FOODS INC","28":"SARGENTO FOODS INC","29":"AMPLE IT SERVICES LLC","30":"AMPLE IT SERVICES LLC","31":"AMPLE IT SERVICES LLC","32":"WHARFEDALE TECHNOLOGIES INC","33":"OXYA CORPORATION","34":"IBM INDIA PRIVATE LIMITED","35":"IBM INDIA PRIVATE LIMITED","36":"ATOS IT SOLUTIONS AND SERVICES INC","37":"AMPLE IT SERVICES LLC","38":"LITTELFUSE INC","39":"TALENTED IT INC","40":"\n","41":"NETEFFECTS INC","42":"MICRON TECHNOLOGY INC","43":"DOTERRA INTERNATIONAL LLC","44":"DOTERRA INTERNATIONAL LLC","45":"DOTERRA INTERNATIONAL LLC","46":"DOTERRA INTERNATIONAL LLC","47":"ATOS IT SOLUTIONS AND SERVICES INC","48":"DATA INC","49":"PACCAR INC","50":"THE CHILDREN'S PLACE SERVICES COMPANY LLC","51":"GENERAL MOTORS COMPANY","52":"PRIMESOURCE BUILDING PRODUCTS INC","53":"TIMET A PCC COMPANY","54":"NEXTLABS INC"},"JOB TITLE":{"0":"SAP BASIS ADMINISTRATOR","1":"SAP BASIS ADMINISTRATOR","2":"SAP BASIS ADMINISTRATOR","3":"SAP BASIS ADMINISTRATOR","4":"SAP BASIS ADMINISTRATOR","5":"SAP BASIS ADMINISTRATOR","6":"SAP BASIS ADMINISTRATOR","7":"SAP BASIS ADMINISTRATOR","8":"SAP BASIS ADMINISTRATOR","9":"SAP BASIS ADMINISTRATOR","10":null,"11":"SAP BASIS ADMINISTRATOR","12":"SAP BASIS ADMINISTRATOR","13":"SAP BASIS ADMINISTRATOR","14":"SAP BASIS ADMINISTRATOR","15":"SAP BASIS ADMINISTRATOR","16":"SAP BASIS ADMINISTRATOR","17":"SAP BASIS ADMINISTRATOR","18":"SAP BASIS ADMINISTRATOR","19":"SAP BASIS ADMINISTRATOR","20":"SAP BASIS ADMINISTRATOR","21":"SAP BASIS ADMINISTRATOR","22":"SAP BASIS ADMINISTRATOR","23":"SAP BASIS ADMINISTRATOR","24":"SAP BASIS ADMINISTRATOR","25":"SAP BASIS ADMINISTRATOR","26":"SAP BASIS ADMINISTRATOR","27":"SAP BASIS ADMINISTRATOR","28":"SAP BASIS ADMINISTRATOR","29":"SAP BASIS ADMINISTRATOR","30":"SAP BASIS ADMINISTRATOR","31":"SAP BASIS ADMINISTRATOR","32":"SAP BASIS ADMINISTRATOR","33":"SAP BASIS ADMINISTRATOR","34":"SAP BASIS ADMINISTRATOR","35":"SAP BASIS ADMINISTRATOR","36":"SAP BASIS ADMINISTRATOR","37":"SAP BASIS ADMINISTRATOR","38":"SAP BASIS ADMINISTRATOR","39":"SAP BASIS ADMINISTRATOR","40":null,"41":"SAP BASIS ADMINISTRATOR","42":"SAP BASIS ADMINISTRATOR","43":"SAP BASIS ADMINISTRATOR","44":"SAP BASIS ADMINISTRATOR","45":"SAP BASIS ADMINISTRATOR","46":"SAP BASIS ADMINISTRATOR","47":"SAP BASIS ADMINISTRATOR","48":"SAP BASIS ADMINISTRATOR","49":"SAP BASIS ADMINISTRATOR","50":"SAP BASIS ADMINISTRATOR","51":"SAP BASIS ADMINISTRATOR","52":"SAP BASIS ADMINISTRATOR","53":"SAP BASIS ADMINISTRATOR","54":"SAP BASIS ADMINISTRATOR"},"BASE SALARY":{"0":"140,000","1":"9,272","2":"50,752","3":"55,000","4":"55,000","5":"60,000","6":"60,000","7":"60,000","8":"60,100","9":"61,500","10":null,"11":"61,734","12":"62,442","13":"62,442","14":"62,566","15":"65,000","16":"66,000","17":"67,475","18":"70,000","19":"70,000","20":"70,000","21":"70,000","22":"70,000","23":"70,221","24":"72,000","25":"75,000","26":"75,000","27":"78,409","28":"78,409","29":"80,000","30":"80,000","31":"80,000","32":"80,000","33":"81,578","34":"81,837","35":"81,837","36":"85,000","37":"86,000","38":"88,000","39":"90,000","40":null,"41":"90,000","42":"94,500","43":"100,000","44":"100,000","45":"100,000","46":"100,000","47":"100,000","48":"100,000","49":"106,600","50":"115,000","51":"115,000","52":"116,000","53":"120,000","54":"130,000"},"LOCATION":{"0":"TEMPE, AZ","1":"LOS ANGELES, CA","2":"NEW YORK, NY","3":"MENOMONEE FALLS, WI","4":"PEACHTREE CITY, GA","5":"ALPHARETTA, GA","6":"IRVING, TX","7":"JERSEY CITY, NJ","8":"NEW BRUNSWICK, NJ","9":"CHARLOTTE, NC","10":null,"11":"PROVIDENCE, RI","12":"DUBLIN, OH","13":"DUBLIN, OH","14":"HOUSTON, TX","15":"IRVING, TX","16":"PHOENIX, AZ","17":"LAKE ZURICH, IL","18":"DEERFIELD, IL","19":"MOUNDS VIEW, MN","20":"OKLAHOMA CITY, OK","21":"PISCATAWAY, NJ","22":"PISCATAWAY, NJ","23":"WILMINGTON, DE","24":"DETROIT, MI","25":"COLLEYVILLE, TX","26":"HOUSTON, TX","27":"PLYMOUTH, WI","28":"PLYMOUTH, WI","29":"PLANO, TX","30":"NEW YORK, NY","31":"FRISCO, TX","32":"LAWRENCEVILLE, NJ","33":"ENGLEWOOD, CO","34":"WAUKEGAN, IL","35":"WAUKEGAN, IL","36":"SAINT LOUIS, MO","37":"RICHARDSON, TX","38":"CHICAGO, IL","39":"NEWTON SQUARE, PA","40":null,"41":"ST. LOUIS, MO","42":"BOISE, ID","43":"PLEASANT GROVE, UT","44":"PLEASANT GROVE, UT","45":"PLEASANT GROVE, UT","46":"PLEASANT GROVE, UT","47":"EUREKA, MO","48":"MONTVALE, NY","49":"RENTON, WA","50":"SECAUCUS, NJ","51":"ROSWELL, GA","52":"IRVING, TX","53":"EXTON, PA","54":"SAN MATEO, CA"},"SUBMIT DATE":{"0":"06\/08\/2016","1":"06\/30\/2016","2":"05\/04\/2016","3":"04\/05\/2016","4":"11\/04\/2016","5":"03\/21\/2016","6":"09\/19\/2016","7":"11\/02\/2016","8":"03\/23\/2016","9":"09\/16\/2016","10":null,"11":"08\/12\/2016","12":"03\/29\/2016","13":"03\/29\/2016","14":"03\/19\/2016","15":"12\/22\/2016","16":"01\/06\/2016","17":"03\/24\/2016","18":"03\/18\/2016","19":"05\/31\/2016","20":"03\/09\/2016","21":"05\/31\/2016","22":"05\/31\/2016","23":"12\/12\/2016","24":"02\/22\/2016","25":"03\/10\/2016","26":"04\/21\/2016","27":"06\/13\/2016","28":"06\/16\/2016","29":"02\/18\/2016","30":"05\/09\/2016","31":"01\/21\/2016","32":"10\/25\/2016","33":"12\/16\/2016","34":"01\/25\/2016","35":"02\/26\/2016","36":"10\/27\/2016","37":"09\/01\/2016","38":"03\/09\/2016","39":"12\/02\/2016","40":null,"41":"03\/10\/2016","42":"02\/27\/2016","43":"09\/30\/2016","44":"09\/30\/2016","45":"09\/30\/2016","46":"10\/04\/2016","47":"06\/22\/2016","48":"09\/13\/2016","49":"09\/29\/2016","50":"05\/16\/2016","51":"08\/15\/2016","52":"12\/07\/2016","53":"02\/02\/2016","54":"03\/04\/2016"},"START DATE":{"0":"07\/01\/2016","1":"12\/09\/2016","2":"08\/26\/2016","3":"09\/16\/2016","4":"11\/14\/2016","5":"03\/28\/2016","6":"10\/02\/2016","7":"11\/10\/2016","8":"09\/22\/2016","9":"10\/03\/2016","10":null,"11":"08\/22\/2016","12":"03\/29\/2016","13":"03\/29\/2016","14":"09\/18\/2016","15":"01\/03\/2017","16":"01\/25\/2016","17":"08\/25\/2016","18":"09\/16\/2016","19":"07\/06\/2016","20":"09\/08\/2016","21":"07\/23\/2016","22":"07\/23\/2016","23":"12\/12\/2016","24":"08\/20\/2016","25":"09\/09\/2016","26":"04\/21\/2016","27":"08\/01\/2016","28":"08\/01\/2016","29":"02\/29\/2016","30":"05\/09\/2016","31":"04\/13\/2016","32":"11\/04\/2016","33":"01\/09\/2017","34":"07\/26\/2016","35":"08\/27\/2016","36":"11\/07\/2016","37":"09\/07\/2016","38":"09\/01\/2016","39":"01\/01\/2017","40":null,"41":"03\/21\/2016","42":"08\/26\/2016","43":"10\/18\/2016","44":"10\/18\/2016","45":"10\/18\/2016","46":"10\/18\/2016","47":"07\/06\/2016","48":"09\/19\/2016","49":"03\/21\/2017","50":"05\/23\/2016","51":"09\/30\/2016","52":"04\/16\/2017","53":"06\/04\/2016","54":"03\/14\/2016"}},"7":{"EMPLOYER":{"0":"MADDISOFT LLC","1":"MADDISOFT LLC","2":"MADDISOFT LLC","3":"LOS ANGELES UNIFIED SCHOOL DISTRICT","4":"RADIANT INFOSYS INC","5":"RADIANT INFOSYS INC","6":"IT TRAILBLAZERS LLC","7":"TRINE IT INC","8":"QUANTUM INTEGRATORS GROUP LLC","9":"MEAD JOHNSON & COMPANY LLC","10":" Ezoic - mid_content - mid_content ","11":"BIJJAM INFORMATION TECHNOLOGIES INC","12":"REVERE INFO TECH INC","13":"REVERE INFO TECH INC","14":"AHU TECHNOLOGIES INC","15":"IT TRAILBLAZERS LLC","16":"PYRAMID TECHNOLOGY SOLUTIONS INC","17":"QUANTUM INTEGRATORS GROUP LLC","18":"BIJJAM INFORMATION TECHNOLOGIES INC","19":"LOGIC PLANET INC","20":"LOGIC PLANET INC","21":"ONE GLOBAL BUSINESS SERVICES LLC","22":"ONE GLOBAL BUSINESS SERVICES LLC","23":"INFINITY TECH GROUP INC","24":"MOLEX LLC","25":"PYRAMID TECHNOLOGY SOLUTIONS INC","26":"IT SPIN INC","27":"CEDENT CONSULTING INC","28":"CEDENT CONSULTING INC","29":"OXYA CORPORATION","30":"RADIANT INFOSYS INC","31":"IBM INDIA PRIVATE LIMITED","32":"ONE GLOBAL BUSINESS SERVICES LLC","33":"ONE GLOBAL BUSINESS SERVICES LLC","34":"WHARFEDALE TECHNOLOGIES INC","35":"TECH MATRIX INC","36":"TECH MATRIX INC","37":"TECH MATRIX INC","38":"JAFIA LLC","39":"CORPORATE SOLUTIONS GENERAL INC","40":"\n","41":"IGT","42":"CORPORATE SOLUTIONS GENERAL INC","43":"CORPORATE SOLUTIONS GENERAL INC","44":"SCHRILL TECHNOLOGIES INC","45":"TALENTED IT INC","46":"TALENTED IT INC","47":"TALENTED IT INC","48":"CARMEUSE LIME & STONE INC","49":"ERP ANALYSTS INC","50":"ERP ANALYSTS INC","51":"CNET GLOBAL SOLUTIONS INC","52":"DAY & ZIMMERMANN INC","53":"CORPORATE SOLUTIONS GENERAL INC","54":"DATA SYSTEMS INTEGRATION GROUP INC","55":"CORPORATE SOLUTIONS GENERAL INC","56":"CNET GLOBAL SOLUTIONS INC","57":"LITTELFUSE INC","58":"VISTEX INC","59":"MALLESWARI INC","60":"SCHRILL TECHNOLOGIES INC","61":"AIR PRODUCTS AND CHEMICALS INC","62":"DATA INC","63":"FMC CORPORATION","64":"TOWN PUMP INC","65":"TOWN PUMP INC","66":"SPLN INTERNATIONAL LLC","67":"EATON CORPORATION","68":"ORBIS INC","69":"APEX ANALYTIX INC","70":"ROBERT BOSCH LLC","71":"ROBERT BOSCH LLC","72":"ARCHENTS INC","73":"ST JUDE MEDICAL BUSINESS SERVICES INC","74":"COPART INC","75":"ZULILY LLC","76":"AIG EMPLOYEE SERVICES INC","77":"LOVE'S TRAVEL STOPS & COUNTRY STORES INC","78":"LOVE'S TRAVEL STOPS & COUNTRY STORES INC","79":"VIVINT INC","80":"BIO-RAD LABORATORIES INC","81":"\n","82":"NEXTLABS INC","83":"CNET GLOBAL SOLUTIONS INC","84":"DISCOVERY COMMUNICATIONS LLC","85":"BIO-RAD LABORATORIES INC"},"JOB TITLE":{"0":"SAP BASIS ADMINISTRATOR","1":"SAP BASIS ADMINISTRATOR","2":"SAP BASIS ADMINISTRATOR","3":"SAP BASIS ADMINISTRATOR","4":"SAP BASIS ADMINISTRATOR","5":"SAP BASIS ADMINISTRATOR","6":"SAP BASIS ADMINISTRATOR","7":"SAP BASIS ADMINISTRATOR","8":"SAP BASIS ADMINISTRATOR","9":"SAP BASIS ADMINISTRATOR","10":null,"11":"SAP BASIS ADMINISTRATOR","12":"SAP BASIS ADMINISTRATOR","13":"SAP BASIS ADMINISTRATOR","14":"SAP BASIS ADMINISTRATOR","15":"SAP BASIS ADMINISTRATOR","16":"SAP BASIS ADMINISTRATOR","17":"SAP BASIS ADMINISTRATOR","18":"SAP BASIS ADMINISTRATOR","19":"SAP BASIS ADMINISTRATOR","20":"SAP BASIS ADMINISTRATOR","21":"SAP BASIS ADMINISTRATOR","22":"SAP BASIS ADMINISTRATOR","23":"SAP BASIS ADMINISTRATOR","24":"SAP BASIS ADMINISTRATOR","25":"SAP BASIS ADMINISTRATOR","26":"SAP BASIS ADMINISTRATOR","27":"SAP BASIS ADMINISTRATOR","28":"SAP BASIS ADMINISTRATOR","29":"SAP BASIS ADMINISTRATOR","30":"SAP BASIS ADMINISTRATOR","31":"SAP BASIS ADMINISTRATOR","32":"SAP BASIS ADMINISTRATOR","33":"SAP BASIS ADMINISTRATOR","34":"SAP BASIS ADMINISTRATOR","35":"SAP BASIS ADMINISTRATOR","36":"SAP BASIS ADMINISTRATOR","37":"SAP BASIS ADMINISTRATOR","38":"SAP BASIS ADMINISTRATOR","39":"SAP BASIS ADMINISTRATOR","40":null,"41":"SAP BASIS ADMINISTRATOR","42":"SAP BASIS ADMINISTRATOR","43":"SAP BASIS ADMINISTRATOR","44":"SAP BASIS ADMINISTRATOR","45":"SAP BASIS ADMINISTRATOR","46":"SAP BASIS ADMINISTRATOR","47":"SAP BASIS ADMINISTRATOR","48":"SAP BASIS ADMINISTRATOR","49":"SAP BASIS ADMINISTRATOR","50":"SAP BASIS ADMINISTRATOR","51":"SAP BASIS ADMINISTRATOR","52":"SAP BASIS ADMINISTRATOR","53":"SAP BASIS ADMINISTRATOR","54":"SAP BASIS ADMINISTRATOR","55":"SAP BASIS ADMINISTRATOR","56":"SAP BASIS ADMINISTRATOR","57":"SAP BASIS ADMINISTRATOR","58":"SAP BASIS ADMINISTRATOR","59":"SAP BASIS ADMINISTRATOR","60":"SAP BASIS ADMINISTRATOR","61":"SAP BASIS ADMINISTRATOR","62":"SAP BASIS ADMINISTRATOR","63":"SAP BASIS ADMINISTRATOR","64":"SAP BASIS ADMINISTRATOR","65":"SAP BASIS ADMINISTRATOR","66":"SAP BASIS ADMINISTRATOR","67":"SAP BASIS ADMINISTRATOR","68":"SAP BASIS ADMINISTRATOR","69":"SAP BASIS ADMINISTRATOR","70":"SAP BASIS ADMINISTRATOR","71":"SAP BASIS ADMINISTRATOR","72":"SAP BASIS ADMINISTRATOR","73":"SAP BASIS ADMINISTRATOR","74":"SAP BASIS ADMINISTRATOR","75":"SAP BASIS ADMINISTRATOR","76":"SAP BASIS ADMINISTRATOR","77":"SAP BASIS ADMINISTRATOR","78":"SAP BASIS ADMINISTRATOR","79":"SAP BASIS ADMINISTRATOR","80":"SAP BASIS ADMINISTRATOR","81":null,"82":"SAP BASIS ADMINISTRATOR","83":"SAP BASIS ADMINISTRATOR","84":"SAP BASIS ADMINISTRATOR","85":"SAP BASIS ADMINISTRATOR"},"BASE SALARY":{"0":"140,000","1":"160,000","2":"160,000","3":"9,272","4":"54,309","5":"54,309","6":"55,000","7":"60,000","8":"60,000","9":"61,859","10":null,"11":"63,000","12":"64,000","13":"64,000","14":"65,000","15":"65,000","16":"65,770","17":"67,000","18":"70,000","19":"71,000","20":"71,000","21":"72,000","22":"72,000","23":"73,278","24":"74,339","25":"74,651","26":"75,000","27":"75,000","28":"75,000","29":"77,314","30":"78,000","31":"78,331","32":"79,000","33":"79,000","34":"80,000","35":"80,000","36":"80,000","37":"80,000","38":"80,392","39":"81,000","40":null,"41":"82,867","42":"84,000","43":"84,000","44":"84,000","45":"86,000","46":"86,000","47":"86,500","48":"87,000","49":"89,024","50":"89,024","51":"90,000","52":"90,000","53":"90,000","54":"90,000","55":"90,000","56":"90,000","57":"92,000","58":"92,000","59":"93,000","60":"95,000","61":"96,949","62":"98,000","63":"99,195","64":"100,000","65":"100,000","66":"100,000","67":"103,688","68":"105,000","69":"105,000","70":"107,422","71":"107,525","72":"108,000","73":"108,214","74":"108,430","75":"110,000","76":"114,130","77":"120,000","78":"120,000","79":"125,000","80":"128,107","81":null,"82":"130,000","83":"130,000","84":"131,194","85":"159,972"},"LOCATION":{"0":"BOISE, ID","1":"CHARLOTTE, NC","2":"SAN JOSE, CA","3":"LOS ANGELES, CA","4":"COLLEYVILLE, TX","5":"COLLEYVILLE, TX","6":"OKLAHOMA CITY, OK","7":"SUWANEE, GA","8":"SOUTHFIELD, MI","9":"EVANSVILLE, IN","10":null,"11":"PLYMOUTH, WI","12":"HOUSTON, TX","13":"HOUSTON, TX","14":"EATONTOWN, NJ","15":"THE WOODLANDS, TX","16":"COLUMBUS, IN","17":"HOUSTON,, TX","18":"DUBLIN, OH","19":"DETROIT, MI","20":"DETROIT, MI","21":"SPRING, TX","22":"PLANO, TX","23":"DUBLIN, OH","24":"LISLE, IL","25":"COLUMBUS, IN","26":"FRISCO, TX","27":"RUMFORD, RI","28":"MARLBOROUGH, MA","29":"JERSEY CITY, NJ","30":"BELLEVUE, WA","31":"GREENSBORO, NC","32":"COPPELL, TX","33":"COPPELL, TX","34":"FORT MYERS, FL","35":"WHITE PLAINS, NY","36":"WHITE PLAINS, NY","37":"WHITE PLAINS, NY","38":"PISCATAWAY, NJ","39":"BARTLESVILLE, OK","40":null,"41":"RENO, NV","42":"BARTLESVILLE, OK","43":"EVANSVILLE, IN","44":"BARTLESVILLE, OK","45":"NEWTOWN SQUARE, PA","46":"NEWTOWN SQUARE, PA","47":"SOUTH SAN FRANCISCO, CA","48":"PITTSBURGH, PA","49":"COPPELL, TX","50":"SOUTHFIELD, MI","51":"SANTA CLARA, CA","52":"PHILADELPHIA, PA","53":"FORT WORTH, TX","54":"DUBLIN, OH","55":"BOLINGBROOK, IL","56":"AUSTIN, TX","57":"CHICAGO, IL","58":"HOFFMAN ESTATES, IL","59":"MEQUON, WI","60":"THE WOODLANDS, TX","61":"ALLENTOWN, PA","62":"MONTVALE, NJ","63":"PHILADELPHIA, PA","64":"BUTTE, MT","65":"BUTTE, MT","66":"WILMINGTON, DE","67":"PEACHTREE CITY, GA","68":"PISCATAWAY, NJ","69":"GREENSBORO, NC","70":"MT. PROSPECT, IL","71":"MT. PROSPECT, IL","72":"LITTLE ELM, TX","73":"MINNETONKA, MN","74":"DALLAS, TX","75":"SEATTLE, WA","76":"BERKELEY HEIGHTS, NJ","77":"OKLAHOMA CITY, OK","78":"OKLAHOMA CITY, OK","79":"LEHI, UT","80":"HERCULES, CA","81":null,"82":"SAN MATEO, CA","83":"AUSTIN, TX","84":"SILVER SPRING, MD","85":"HERCULES, CA"},"SUBMIT DATE":{"0":"07\/19\/2017","1":"10\/03\/2017","2":"07\/19\/2017","3":"01\/10\/2017","4":"03\/08\/2017","5":"03\/08\/2017","6":"03\/21\/2017","7":"03\/03\/2017","8":"02\/06\/2017","9":"02\/22\/2017","10":null,"11":"12\/25\/2017","12":"03\/21\/2017","13":"03\/22\/2017","14":"03\/06\/2017","15":"06\/16\/2017","16":"01\/25\/2017","17":"12\/11\/2017","18":"04\/14\/2017","19":"09\/06\/2017","20":"09\/13\/2017","21":"03\/07\/2017","22":"03\/07\/2017","23":"07\/13\/2017","24":"07\/13\/2017","25":"01\/25\/2017","26":"02\/20\/2017","27":"03\/08\/2017","28":"07\/19\/2017","29":"06\/14\/2017","30":"06\/02\/2017","31":"08\/28\/2017","32":"01\/19\/2017","33":"01\/19\/2017","34":"03\/23\/2017","35":"02\/15\/2017","36":"02\/15\/2017","37":"02\/03\/2017","38":"08\/17\/2017","39":"02\/20\/2017","40":null,"41":"01\/20\/2017","42":"11\/10\/2017","43":"09\/22\/2017","44":"11\/13\/2017","45":"01\/12\/2017","46":"01\/19\/2017","47":"06\/02\/2017","48":"03\/03\/2017","49":"09\/20\/2017","50":"09\/20\/2017","51":"03\/17\/2017","52":"02\/24\/2017","53":"02\/09\/2017","54":"04\/21\/2017","55":"05\/16\/2017","56":"06\/02\/2017","57":"03\/10\/2017","58":"10\/10\/2017","59":"02\/28\/2017","60":"05\/21\/2017","61":"12\/18\/2017","62":"01\/31\/2017","63":"11\/16\/2017","64":"08\/10\/2017","65":"08\/14\/2017","66":"09\/21\/2017","67":"09\/26\/2017","68":"03\/15\/2017","69":"02\/13\/2017","70":"04\/06\/2017","71":"04\/07\/2017","72":"08\/29\/2017","73":"05\/02\/2017","74":"08\/31\/2017","75":"04\/14\/2017","76":"12\/22\/2017","77":"12\/22\/2017","78":"12\/22\/2017","79":"03\/22\/2017","80":"01\/04\/2017","81":null,"82":"03\/13\/2017","83":"06\/19\/2017","84":"03\/14\/2017","85":"10\/16\/2017"},"START DATE":{"0":"07\/19\/2017","1":"10\/03\/2017","2":"07\/19\/2017","3":"06\/23\/2017","4":"09\/07\/2017","5":"09\/07\/2017","6":"03\/30\/2017","7":"09\/02\/2017","8":"02\/15\/2017","9":"07\/02\/2017","10":null,"11":"12\/26\/2017","12":"08\/18\/2017","13":"08\/16\/2017","14":"09\/05\/2017","15":"06\/23\/2017","16":"06\/09\/2017","17":"12\/19\/2017","18":"04\/17\/2017","19":"09\/13\/2017","20":"09\/13\/2017","21":"09\/06\/2017","22":"09\/06\/2017","23":"07\/13\/2017","24":"01\/12\/2018","25":"06\/09\/2017","26":"08\/20\/2017","27":"08\/20\/2017","28":"07\/24\/2017","29":"07\/05\/2017","30":"06\/02\/2017","31":"08\/28\/2017","32":"02\/06\/2017","33":"02\/06\/2017","34":"03\/23\/2017","35":"02\/15\/2017","36":"02\/18\/2017","37":"02\/03\/2017","38":"08\/17\/2017","39":"02\/27\/2017","40":null,"41":"07\/02\/2017","42":"11\/27\/2017","43":"10\/02\/2017","44":"11\/27\/2017","45":"01\/12\/2017","46":"01\/19\/2017","47":"06\/12\/2017","48":"08\/25\/2017","49":"09\/27\/2017","50":"09\/27\/2017","51":"09\/01\/2017","52":"08\/08\/2017","53":"02\/20\/2017","54":"09\/25\/2017","55":"05\/29\/2017","56":"07\/03\/2017","57":"09\/01\/2017","58":"11\/06\/2017","59":"02\/28\/2017","60":"10\/27\/2017","61":"04\/20\/2018","62":"02\/13\/2017","63":"12\/01\/2017","64":"09\/11\/2017","65":"09\/11\/2017","66":"10\/05\/2017","67":"03\/11\/2018","68":"09\/08\/2017","69":"02\/27\/2017","70":"09\/01\/2017","71":"08\/20\/2017","72":"08\/29\/2017","73":"05\/10\/2017","74":"02\/08\/2018","75":"10\/13\/2017","76":"03\/09\/2018","77":"01\/17\/2018","78":"01\/17\/2018","79":"03\/30\/2017","80":"05\/16\/2017","81":null,"82":"07\/31\/2017","83":"07\/03\/2017","84":"06\/29\/2017","85":"03\/30\/2018"}},"8":{"EMPLOYER":{"0":"MADDISOFT LLC","1":"PYRAMID TECHNOLOGY SOLUTIONS INC","2":"VENNSYS LLC","3":"MOLEX LLC","4":"QUANTUM INTEGRATORS GROUP LLC","5":"AVCO CONSULTING INC","6":"NPC INTERNATIONAL INC","7":"EMPIRE MERCHANTS NORTH LLC","8":"EMPIRE MERCHANTS NORTH LLC","9":"COVANEX INC","10":" Ezoic - mid_content - mid_content ","11":"AVCO CONSULTING INC","12":"AVCO CONSULTING INC","13":"AMERICAN UNIT INC","14":"CARMEUSE LIME & STONE INC","15":"NUMBERS ONLY INC","16":"SYMMETRY LLC","17":"MERIDIAN TECHNOLOGY SOLUTIONS INC","18":"VISTEX INC","19":"TAWA SUPERMARKET INC","20":"IMPEC IT INC","21":"PROSOFT IT SERVICES INC","22":"PROSOFT IT SERVICES INC","23":"IMPEC IT INC","24":"99 CENTS ONLY STORES INC","25":"TATE AND LYLE AMERICAS LLC","26":"CEPHEID","27":"PACIFIC COAST COMPANIES INC","28":"PACIFIC COAST COMPANIES INC","29":"ENTEGRIS PROFESSIONAL SOLUTIONS INC","30":"RESOURCE LOGISTICS INC","31":"RESOURCE LOGISTICS INC","32":"GENERAL ELECTRIC COMPANY","33":"LABYRINTH SOLUTIONS INC","34":"EATON CORPORATION","35":"NUSKIN INTERNATIONAL INC","36":"BOB'S DISCOUNT FURNITURE LLC","37":"TIMET A PCC COMPANY","38":"TIMET A PCC COMPANY"},"JOB TITLE":{"0":"SAP BASIS ADMINISTRATOR","1":"SAP BASIS ADMINISTRATOR","2":"SAP BASIS ADMINISTRATOR","3":"SAP BASIS ADMINISTRATOR","4":"SAP BASIS ADMINISTRATOR","5":"SAP BASIS ADMINISTRATOR","6":"SAP BASIS ADMINISTRATOR","7":"SAP BASIS ADMINISTRATOR","8":"SAP BASIS ADMINISTRATOR","9":"SAP BASIS ADMINISTRATOR","10":null,"11":"SAP BASIS ADMINISTRATOR","12":"SAP BASIS ADMINISTRATOR","13":"SAP BASIS ADMINISTRATOR","14":"SAP BASIS ADMINISTRATOR","15":"SAP BASIS ADMINISTRATOR","16":"SAP BASIS ADMINISTRATOR","17":"SAP BASIS ADMINISTRATOR","18":"SAP BASIS ADMINISTRATOR","19":"SAP BASIS ADMINISTRATOR","20":"SAP BASIS ADMINISTRATOR","21":"SAP BASIS ADMINISTRATOR","22":"SAP BASIS ADMINISTRATOR","23":"SAP BASIS ADMINISTRATOR","24":"SAP BASIS ADMINISTRATOR","25":"SAP BASIS ADMINISTRATOR","26":"SAP BASIS ADMINISTRATOR","27":"SAP BASIS ADMINISTRATOR","28":"SAP BASIS ADMINISTRATOR","29":"SAP BASIS ADMINISTRATOR","30":"SAP BASIS ADMINISTRATOR","31":"SAP BASIS ADMINISTRATOR","32":"SAP BASIS ADMINISTRATOR","33":"SAP BASIS ADMINISTRATOR","34":"SAP BASIS ADMINISTRATOR","35":"SAP BASIS ADMINISTRATOR","36":"SAP BASIS ADMINISTRATOR","37":"SAP BASIS ADMINISTRATOR","38":"SAP BASIS ADMINISTRATOR"},"BASE SALARY":{"0":"90,000","1":"71,926","2":"74,880","3":"76,253","4":"78,000","5":"78,166","6":"78,682","7":"80,000","8":"80,000","9":"82,500","10":null,"11":"83,512","12":"83,512","13":"83,533","14":"87,948","15":"88,350","16":"88,500","17":"90,000","18":"95,000","19":"95,000","20":"96,000","21":"96,000","22":"100,000","23":"100,000","24":"108,751","25":"110,011","26":"110,864","27":"115,000","28":"115,000","29":"116,293","30":"120,000","31":"120,000","32":"120,000","33":"120,000","34":"125,258","35":"129,598","36":"131,962","37":"132,000","38":"132,000"},"LOCATION":{"0":"BOISE, ID","1":"COLUMBUS, IN","2":"GOLDEN VALLEY, MN","3":"LISLE, IL","4":"MARIETTA, GA","5":"WORCESTER, MA","6":"PITTSBURG, KS","7":"ROCHESTER, NY","8":"WEST COXSACKIE, NY","9":"SECAUCUS, NJ","10":null,"11":"LANSING, MI","12":"WORCESTER, MA","13":"SAN ANTONIO, TX","14":"PITTSBURGH, PA","15":"SOUTHLAKE, TX","16":"BROOKFIELD, WI","17":"OAK BROOK, IL","18":"HOFFMAN ESTATES, IL","19":"BUENA PARK, CA","20":"RALEIGH, NC","21":"RALEIGH, NC","22":"RALEIGH, NC","23":"RALEIGH, NC","24":"KATY, TX","25":"HOFFMAN ESTATES, IL","26":"SUNNYVALE, CA","27":"RANCHO CORDOVA, CA","28":"RANCHO CORDOVA, CA","29":"BILLERICA, MA","30":"ATLANTA, GA","31":"SANDY SPRINGS, GA","32":"SCHENECTADY, NY","33":"WALTHAM, MA","34":"PEACHTREE CITY, GA","35":"PROVO, UT","36":"MANCHESTER, CT","37":"WARRENSVILLE HEIGHTS, OH","38":"WARRENSVILLE HEIGHTS, OH"},"SUBMIT DATE":{"0":"10\/26\/2018","1":"07\/30\/2018","2":"02\/08\/2018","3":"07\/19\/2018","4":"12\/03\/2018","5":"03\/08\/2018","6":"08\/23\/2018","7":"03\/11\/2018","8":"03\/11\/2018","9":"12\/21\/2018","10":null,"11":"03\/21\/2018","12":"03\/08\/2018","13":"06\/25\/2018","14":"02\/01\/2018","15":"08\/04\/2018","16":"04\/12\/2018","17":"02\/16\/2018","18":"06\/05\/2018","19":"05\/24\/2018","20":"06\/01\/2018","21":"06\/01\/2018","22":"08\/13\/2018","23":"08\/13\/2018","24":"04\/30\/2018","25":"11\/27\/2018","26":"03\/14\/2018","27":"04\/03\/2018","28":"04\/12\/2018","29":"01\/31\/2018","30":"03\/22\/2018","31":"08\/31\/2018","32":"07\/02\/2018","33":"01\/25\/2018","34":"07\/05\/2018","35":"08\/14\/2018","36":"04\/17\/2018","37":"10\/19\/2018","38":"10\/19\/2018"},"START DATE":{"0":"10\/29\/2018","1":"01\/27\/2019","2":"03\/26\/2018","3":"01\/12\/2019","4":"12\/11\/2018","5":"09\/04\/2018","6":"12\/28\/2018","7":"09\/07\/2018","8":"09\/06\/2018","9":"01\/07\/2019","10":null,"11":"09\/04\/2018","12":"09\/04\/2018","13":"07\/02\/2018","14":"07\/31\/2018","15":"09\/10\/2018","16":"04\/30\/2018","17":"02\/19\/2018","18":"06\/20\/2018","19":"11\/14\/2018","20":"06\/01\/2018","21":"06\/01\/2018","22":"08\/13\/2018","23":"08\/13\/2018","24":"10\/30\/2018","25":"12\/03\/2018","26":"03\/26\/2018","27":"04\/09\/2018","28":"04\/12\/2018","29":"06\/24\/2018","30":"05\/01\/2018","31":"12\/31\/2018","32":"07\/16\/2018","33":"02\/07\/2018","34":"07\/10\/2018","35":"02\/09\/2019","36":"07\/13\/2018","37":"11\/01\/2018","38":"11\/01\/2018"}},"9":{"EMPLOYER":{"0":"DIGITAL SCRIPTS INC","1":"DIGITAL SCRIPTS INC","2":"LILLI TECHNOLOGY LLC","3":"INSIGHT GLOBAL LLC","4":"LOS ANGELES UNIFIED SCHOOL DISTRICT","5":"V3TECH SOLUTIONS INC","6":"PYRAMID TECHNOLOGY SOLUTIONS INC","7":"LILLI TECHNOLOGY LLC","8":"IT TRAILBLAZERS LLC","9":"CHAIPHON LLC","10":" Ezoic - mid_content - mid_content ","11":"CHAIPHON LLC","12":"CHAIPHON LLC","13":"AMERICAN UNIT INC","14":"AMERICAN UNIT INC","15":"AMPLE IT SERVICES LLC","16":"TAMPA ELECTRIC COMPANY","17":"OXYA CORPORATION","18":"OXYA CORPORATION","19":"OXYA CORPORATION","20":"EMPIRE MERCHANTS NORTH LLC","21":"SECURE-24 LLC","22":"VISTEX INC","23":"MARVEL TECHNOLOGIES INC","24":"DIGITALBYTES INC","25":"DIGITALBYTES INC","26":"AMPLE IT SERVICES LLC","27":"APEX ANALYTIX LLC","28":"QUANTUM INTEGRATORS GROUP LLC","29":"ASSENT SOLUTIONS LLC","30":"IBM CORPORATION","31":"IBM CORPORATION","32":"UV TECHNOLOGY SOLUTIONS INC","33":"TT TECHNOLOGIES INC","34":"CORPORATE SOLUTIONS GENERAL INC","35":"CORPORATE SOLUTIONS GENERAL INC","36":"CORPORATE SOLUTIONS GENERAL INC","37":"ONE GLOBAL BUSINESS SERVICES LLC","38":"DAY & ZIMMERMANN INC","39":"PACCAR INC","40":"\n","41":"IT TRAILBLAZERS LLC","42":"ONE GLOBAL BUSINESS SERVICES LLC","43":"ENTERPRISE SOFTWARE SOLUTIONS INC","44":"NOBEL BIOCARE PROCERA LLC","45":"NATIONAL MEDICAL CARE INC A FRESENIUS MEDICAL CARE NA COMPANY","46":"EPIC SYSTEMS INC","47":"EPIC SYSTEMS INC","48":"EPIC SYSTEMS INC","49":"UV TECHNOLOGY SOLUTIONS INC","50":"GREAT LAKES CHEESE CO INC","51":"HUBS INC","52":"SPX CORPORATION","53":"INTERNATIONAL BUSINESS MACHINES CORPORATION","54":"GORDON FOOD SERVICE INC","55":"THE CHILDREN'S PLACE SERVICES COMPANY LLC","56":"ADVANCED ENERGY INDUSTRIES INC","57":"VIVINT INC","58":"VIVINT INC"},"JOB TITLE":{"0":"SAP BASIS ADMINISTRATOR","1":"SAP BASIS ADMINISTRATOR","2":"SAP BASIS ADMINISTRATOR","3":"SAP BASIS ADMINISTRATOR","4":"SAP BASIS ADMINISTRATOR","5":"SAP BASIS ADMINISTRATOR","6":"SAP BASIS ADMINISTRATOR","7":"SAP BASIS ADMINISTRATOR","8":"SAP BASIS ADMINISTRATOR","9":"SAP BASIS ADMINISTRATOR","10":null,"11":"SAP BASIS ADMINISTRATOR","12":"SAP BASIS ADMINISTRATOR","13":"SAP BASIS ADMINISTRATOR","14":"SAP BASIS ADMINISTRATOR","15":"SAP BASIS ADMINISTRATOR","16":"SAP BASIS ADMINISTRATOR","17":"SAP BASIS ADMINISTRATOR","18":"SAP BASIS ADMINISTRATOR","19":"SAP BASIS ADMINISTRATOR","20":"SAP BASIS ADMINISTRATOR","21":"SAP BASIS ADMINISTRATOR","22":"SAP BASIS ADMINISTRATOR","23":"SAP BASIS ADMINISTRATOR","24":"SAP BASIS ADMINISTRATOR","25":"SAP BASIS ADMINISTRATOR","26":"SAP BASIS ADMINISTRATOR","27":"SAP BASIS ADMINISTRATOR","28":"SAP BASIS ADMINISTRATOR","29":"SAP BASIS ADMINISTRATOR","30":"SAP BASIS ADMINISTRATOR","31":"SAP BASIS ADMINISTRATOR","32":"SAP BASIS ADMINISTRATOR","33":"SAP BASIS ADMINISTRATOR","34":"SAP BASIS ADMINISTRATOR","35":"SAP BASIS ADMINISTRATOR","36":"SAP BASIS ADMINISTRATOR","37":"SAP BASIS ADMINISTRATOR","38":"SAP BASIS ADMINISTRATOR","39":"SAP BASIS ADMINISTRATOR","40":null,"41":"SAP BASIS ADMINISTRATOR","42":"SAP BASIS ADMINISTRATOR","43":"SAP BASIS ADMINISTRATOR","44":"SAP BASIS ADMINISTRATOR","45":"SAP BASIS ADMINISTRATOR","46":"SAP BASIS ADMINISTRATOR","47":"SAP BASIS ADMINISTRATOR","48":"SAP BASIS ADMINISTRATOR","49":"SAP BASIS ADMINISTRATOR","50":"SAP BASIS ADMINISTRATOR","51":"SAP BASIS ADMINISTRATOR","52":"SAP BASIS ADMINISTRATOR","53":"SAP BASIS ADMINISTRATOR","54":"SAP BASIS ADMINISTRATOR","55":"SAP BASIS ADMINISTRATOR","56":"SAP BASIS ADMINISTRATOR","57":"SAP BASIS ADMINISTRATOR","58":"SAP BASIS ADMINISTRATOR"},"BASE SALARY":{"0":"72,400","1":"72,400","2":"72,720","3":"112,740","4":"9,272","5":"62,296","6":"72,842","7":"75,629","8":"78,000","9":"80,000","10":null,"11":"80,000","12":"80,000","13":"80,018","14":"80,413","15":"82,000","16":"82,000","17":"83,512","18":"83,512","19":"83,512","20":"84,050","21":"85,000","22":"86,500","23":"88,670","24":"92,000","25":"92,000","26":"94,000","27":"94,182","28":"95,000","29":"97,656","30":"97,926","31":"97,926","32":"99,424","33":"100,000","34":"100,000","35":"100,000","36":"100,000","37":"100,000","38":"100,090","39":"101,546","40":null,"41":"102,000","42":"105,000","43":"105,000","44":"105,000","45":"105,248","46":"105,768","47":"105,768","48":"105,768","49":"108,077","50":"110,000","51":"111,696","52":"112,000","53":"119,288","54":"120,000","55":"122,200","56":"123,219","57":"125,000","58":"125,000"},"LOCATION":{"0":"PAULSBORO, NJ","1":"PAULSBORO, NJ","2":"RADNOR, PA","3":"SAN DIEGO, CA","4":"LOS ANGELES, CA","5":"FARMINGTON HILLS, MI","6":"COLUMBUS, IN","7":"RADNOR, PA","8":"MOUNDS VIEW, MN","9":"JUPITER, FL","10":null,"11":"JUPITER, FL","12":"JUPITER, FL","13":"IRVING, TX","14":"AUSTIN, TX","15":"DEERFIELD, IL","16":"TAMPA, FL","17":"JERSEY CITY, NJ","18":"JERSEY CITY, NJ","19":"JERSEY CITY, NJ","20":"WEST COXSACKIE, NY","21":"SOUTHFIELD, MI","22":"HOFFMAN ESTATES, IL","23":"CHARLOTTE, NC","24":"DUNDEE, MI","25":"HOUSTON, TX","26":"RICHARDSON, TX","27":"GREENSBORO, NC","28":"RARITAN, NJ","29":"INVER GROVE HEIGHTS, MN","30":"MARYSVILLE, OH","31":"MARYSVILLE, OH","32":"HOPKINTON, MA","33":"HOUSTON, TX","34":"PLANO, TX","35":"PLANO, TX","36":"PLANO, TX","37":"COPPELL, TX","38":"PHILADELPHIA, PA","39":"RENTON, WA","40":null,"41":"THE WOODLANDS, TX","42":"PLANO, TX","43":"LARGO, MD","44":"MAHWAH, NJ","45":"WALTHAM, MA","46":"BARTLESVILLE, OK","47":"BARTLESVILLE, OK","48":"BARTLESVILLE, OK","49":"HOPKINTON, MA","50":"HIRAM, OH","51":"SHELTON, CT","52":"DULUTH, GA","53":"DURHAM, NC","54":"WYOMING, MI","55":"SECAUCUS, NJ","56":"DENVER, CO","57":"EAGLE MOUNTAIN, UT","58":"LEHI, UT"},"SUBMIT DATE":{"0":"02\/26\/2019","1":"03\/31\/2019","2":"06\/11\/2019","3":"11\/26\/2019","4":"06\/10\/2019","5":"03\/20\/2019","6":"12\/10\/2019","7":"06\/11\/2019","8":"01\/30\/2019","9":"03\/13\/2019","10":null,"11":"03\/13\/2019","12":"03\/13\/2019","13":"07\/10\/2019","14":"07\/16\/2019","15":"07\/15\/2019","16":"11\/27\/2019","17":"02\/21\/2019","18":"03\/16\/2019","19":"03\/07\/2019","20":"03\/26\/2019","21":"05\/23\/2019","22":"03\/05\/2019","23":"05\/03\/2019","24":"08\/08\/2019","25":"03\/28\/2019","26":"03\/31\/2019","27":"08\/09\/2019","28":"08\/07\/2019","29":"10\/08\/2019","30":"02\/19\/2019","31":"03\/15\/2019","32":"02\/01\/2019","33":"05\/17\/2019","34":"08\/28\/2019","35":"08\/28\/2019","36":"08\/29\/2019","37":"12\/30\/2019","38":"11\/11\/2019","39":"10\/17\/2019","40":null,"41":"06\/25\/2019","42":"11\/19\/2019","43":"09\/09\/2019","44":"03\/04\/2019","45":"05\/13\/2019","46":"11\/05\/2019","47":"11\/08\/2019","48":"11\/15\/2019","49":"03\/21\/2019","50":"05\/06\/2019","51":"09\/04\/2019","52":"11\/22\/2019","53":"10\/09\/2019","54":"02\/12\/2019","55":"02\/01\/2019","56":"07\/10\/2019","57":"10\/16\/2019","58":"10\/17\/2019"},"START DATE":{"0":"08\/28\/2019","1":"08\/28\/2019","2":"06\/24\/2019","3":"12\/09\/2019","4":"12\/09\/2019","5":"09\/01\/2019","6":"06\/09\/2020","7":"06\/24\/2019","8":"02\/07\/2019","9":"09\/01\/2019","10":null,"11":"09\/01\/2019","12":"09\/01\/2019","13":"07\/19\/2019","14":"07\/29\/2019","15":"09\/15\/2019","16":"01\/01\/2020","17":"08\/15\/2019","18":"09\/15\/2019","19":"08\/15\/2019","20":"09\/24\/2019","21":"05\/31\/2019","22":"03\/13\/2019","23":"05\/27\/2019","24":"08\/15\/2019","25":"04\/04\/2019","26":"09\/08\/2019","27":"02\/04\/2020","28":"08\/15\/2019","29":"10\/28\/2019","30":"08\/18\/2019","31":"09\/14\/2019","32":"02\/08\/2019","33":"08\/01\/2019","34":"09\/03\/2019","35":"09\/03\/2019","36":"09\/03\/2019","37":"02\/05\/2020","38":"04\/20\/2020","39":"03\/21\/2020","40":null,"41":"09\/17\/2019","42":"02\/06\/2020","43":"09\/16\/2019","44":"08\/23\/2019","45":"10\/17\/2019","46":"11\/11\/2019","47":"11\/18\/2019","48":"12\/02\/2019","49":"03\/28\/2019","50":"05\/28\/2019","51":"02\/10\/2020","52":"12\/01\/2019","53":"11\/04\/2019","54":"02\/20\/2019","55":"05\/23\/2019","56":"07\/15\/2019","57":"03\/31\/2020","58":"03\/31\/2020"}},"10":{"EMPLOYER":{"0":"V3TECH SOLUTIONS INC","1":"NGK SPARK PLUGS (USA) INC","2":"AMZUR TECHNOLOGIES INC","3":"AMZUR TECHNOLOGIES INC","4":"EMPIRE MERCHANTS NORTH LLC","5":"COGENT INTEGRATED BUSINESS SOLUTIONS INC","6":"SCHRILL TECHNOLOGIES INC","7":"SCHRILL TECHNOLOGIES INC","8":"COVANEX INC","9":"PLANTEK LLC","10":" Ezoic - mid_content - mid_content ","11":"PLANTEK LLC","12":"SECURE-24 LLC","13":"AMZUR TECHNOLOGIES INC","14":"COVANEX INC","15":"DIGITALBYTES INC","16":"INTERNATIONAL PAPER","17":"AMZUR TECHNOLOGIES INC","18":"CORPORATE SOLUTIONS GENERAL INC","19":"CORPORATE SOLUTIONS GENERAL INC","20":"CORPORATE SOLUTIONS GENERAL INC","21":"VISTEX INC","22":"KN TECH SOLUTIONS LLC","23":"ASSENT SOLUTIONS LLC","24":"APPLE AMERICAN GROUP LLC","25":"INDU LLC","26":"FMC CORPORATION","27":"GREAT LAKES CHEESE CO INC","28":"GREAT LAKES CHEESE CO INC","29":"SECURE-24 LLC","30":"COPART INC","31":"EPIC SYSTEMS INC","32":"EPIC SYSTEMS INC","33":"SOPHUS IT SOLUTIONS LLC","34":"AIG EMPLOYEE SERVICES INC","35":"INTERNATIONAL BUSINESS MACHINES CORPORATION","36":"DIGITALBYTES INC","37":"DIGITALBYTES INC","38":"GENERAC POWER SYSTEMS INC","39":"INCIPIENT CORPORATION"},"JOB TITLE":{"0":"SAP BASIS ADMINISTRATOR","1":"SAP BASIS ADMINISTRATOR","2":"SAP BASIS ADMINISTRATOR","3":"SAP BASIS ADMINISTRATOR","4":"SAP BASIS ADMINISTRATOR","5":"SAP BASIS ADMINISTRATOR","6":"SAP BASIS ADMINISTRATOR","7":"SAP BASIS ADMINISTRATOR","8":"SAP BASIS ADMINISTRATOR","9":"SAP BASIS ADMINISTRATOR","10":null,"11":"SAP BASIS ADMINISTRATOR","12":"SAP BASIS ADMINISTRATOR","13":"SAP BASIS ADMINISTRATOR","14":"SAP BASIS ADMINISTRATOR","15":"SAP BASIS ADMINISTRATOR","16":"SAP BASIS ADMINISTRATOR","17":"SAP BASIS ADMINISTRATOR","18":"SAP BASIS ADMINISTRATOR","19":"SAP BASIS ADMINISTRATOR","20":"SAP BASIS ADMINISTRATOR","21":"SAP BASIS ADMINISTRATOR","22":"SAP BASIS ADMINISTRATOR","23":"SAP BASIS ADMINISTRATOR","24":"SAP BASIS ADMINISTRATOR","25":"SAP BASIS ADMINISTRATOR","26":"SAP BASIS ADMINISTRATOR","27":"SAP BASIS ADMINISTRATOR","28":"SAP BASIS ADMINISTRATOR","29":"SAP BASIS ADMINISTRATOR","30":"SAP BASIS ADMINISTRATOR","31":"SAP BASIS ADMINISTRATOR","32":"SAP BASIS ADMINISTRATOR","33":"SAP BASIS ADMINISTRATOR","34":"SAP BASIS ADMINISTRATOR","35":"SAP BASIS ADMINISTRATOR","36":"SAP BASIS ADMINISTRATOR","37":"SAP BASIS ADMINISTRATOR","38":"SAP BASIS ADMINISTRATOR","39":"SAP BASIS ADMINISTRATOR"},"BASE SALARY":{"0":"70,000","1":"72,100","2":"74,152","3":"74,152","4":"75,000","5":"75,150","6":"78,021","7":"78,021","8":"84,000","9":"84,947","10":null,"11":"84,947","12":"85,000","13":"87,256","14":"88,000","15":"92,000","16":"94,010","17":"96,179","18":"96,470","19":"96,470","20":"96,470","21":"97,850","22":"99,736","23":"105,726","24":"108,000","25":"109,000","26":"109,533","27":"110,000","28":"110,000","29":"111,072","30":"111,191","31":"111,654","32":"111,654","33":"113,381","34":"114,962","35":"119,288","36":"120,000","37":"120,000","38":"124,000","39":"150,010"},"LOCATION":{"0":"FARMINGTON HILLS, MI","1":"WIXOM, MI","2":"LAS VEGAS, NV","3":"LAS VEGAS, NV","4":"MALVERN, PA","5":"BINGHAM FARMS, MI","6":"THE WOODLANDS, TX","7":"THE WOODLANDS, TX","8":"GREENFIELD, IN","9":"SUNNYVALE, CA","10":null,"11":"SUNNYVALE, CA","12":"PALATINE, IL","13":"LAS VEGAS, NV","14":"GREENFIELD, IN","15":"SUGAR LAND, TX","16":"MEMPHIS, TN","17":"LAS VEGAS, NV","18":"PLANO, TX","19":"PLANO, TX","20":"PLANO, TX","21":"HOFFMAN ESTATES, IL","22":"BARTLESVILLE, OK","23":"INVER GROVE HEIGHTS, MN","24":"INDEPENDENCE, OH","25":"PLANO, TX","26":"PHILADELPHIA, PA","27":"HIRAM, OH","28":"HIRAM, OH","29":"SOUTHFIELD, MI","30":"DALLAS, TX","31":"BARTLESVILLE, OK","32":"BARTLESVILLE, OK","33":"REDMOND, WA","34":"PARSIPPANY, NJ","35":"DURHAM, NC","36":"SUGAR LAND, TX","37":"SUGAR LAND, TX","38":"WAUKESHA, WI","39":"RUTHERFORD, NJ"},"SUBMIT DATE":{"0":"04\/20\/2020","1":"03\/18\/2020","2":"03\/04\/2020","3":"03\/04\/2020","4":"10\/07\/2020","5":"09\/04\/2020","6":"04\/07\/2020","7":"04\/30\/2020","8":"05\/11\/2020","9":"06\/12\/2020","10":null,"11":"06\/12\/2020","12":"01\/31\/2020","13":"02\/04\/2020","14":"08\/25\/2020","15":"04\/09\/2020","16":"04\/06\/2020","17":"02\/04\/2020","18":"04\/13\/2020","19":"04\/13\/2020","20":"02\/21\/2020","21":"12\/30\/2020","22":"05\/22\/2020","23":"07\/21\/2020","24":"08\/06\/2020","25":"06\/09\/2020","26":"04\/23\/2020","27":"05\/28\/2020","28":"08\/13\/2020","29":"05\/27\/2020","30":"08\/04\/2020","31":"10\/03\/2020","32":"10\/03\/2020","33":"03\/09\/2020","34":"10\/07\/2020","35":"01\/17\/2020","36":"04\/14\/2020","37":"05\/11\/2020","38":"05\/19\/2020","39":"11\/02\/2020"},"START DATE":{"0":"10\/01\/2020","1":"09\/17\/2020","2":"03\/04\/2020","3":"03\/04\/2020","4":"10\/19\/2020","5":"09\/14\/2020","6":"10\/01\/2020","7":"10\/01\/2020","8":"05\/11\/2020","9":"06\/23\/2020","10":null,"11":"06\/23\/2020","12":"02\/03\/2020","13":"02\/04\/2020","14":"12\/31\/2020","15":"04\/16\/2020","16":"08\/23\/2020","17":"02\/04\/2020","18":"06\/04\/2020","19":"04\/20\/2020","20":"06\/04\/2020","21":"06\/20\/2021","22":"10\/01\/2020","23":"10\/09\/2020","24":"08\/17\/2020","25":"10\/14\/2020","26":"10\/19\/2020","27":"06\/22\/2020","28":"08\/31\/2020","29":"09\/03\/2020","30":"02\/03\/2021","31":"12\/30\/2020","32":"12\/09\/2020","33":"04\/01\/2020","34":"03\/09\/2021","35":"01\/27\/2020","36":"07\/02\/2020","37":"05\/18\/2020","38":"06\/01\/2020","39":"11\/02\/2020"}}}}