{"Year":{"0":2010,"1":2011,"2":2012,"3":2013,"4":2014,"5":2015,"6":2016,"7":2017,"8":2018,"9":2019,"10":2020},"Job Title":{"0":"Retirement Business Analyst","1":"Retirement Business Analyst","2":"Retirement Business Analyst","3":"Retirement Business Analyst","4":"Retirement Business Analyst","5":"Retirement Business Analyst","6":"Retirement Business Analyst","7":"Retirement Business Analyst","8":"Retirement Business Analyst","9":"Retirement Business Analyst","10":"Retirement Business Analyst"},"Table":{"0":null,"1":null,"2":null,"3":null,"4":null,"5":null,"6":null,"7":null,"8":null,"9":null,"10":null}}