{"Year":{"0":2010,"1":2011,"2":2012,"3":2013,"4":2014,"5":2015,"6":2016,"7":2017,"8":2018,"9":2019,"10":2020},"Job Title":{"0":"Fire Alarm Technician","1":"Fire Alarm Technician","2":"Fire Alarm Technician","3":"Fire Alarm Technician","4":"Fire Alarm Technician","5":"Fire Alarm Technician","6":"Fire Alarm Technician","7":"Fire Alarm Technician","8":"Fire Alarm Technician","9":"Fire Alarm Technician","10":"Fire Alarm Technician"},"Table":{"0":null,"1":null,"2":null,"3":null,"4":null,"5":null,"6":null,"7":null,"8":null,"9":null,"10":null}}