{"Year":{"0":2010,"1":2011,"2":2012,"3":2013,"4":2014,"5":2015,"6":2016,"7":2017,"8":2018,"9":2019,"10":2020},"Job Title":{"0":"IT Administrator","1":"IT Administrator","2":"IT Administrator","3":"IT Administrator","4":"IT Administrator","5":"IT Administrator","6":"IT Administrator","7":"IT Administrator","8":"IT Administrator","9":"IT Administrator","10":"IT Administrator"},"Table":{"0":null,"1":null,"2":null,"3":null,"4":null,"5":{"EMPLOYER":{"0":"REBEL ATHLETIC INC","1":"LAS COLINAS INTERNATIONAL INC","2":"WAVETECH SYSTEMS LLC","3":"H5","4":"SUNSET POOL INC","5":"SUNSET POOL INC","6":"INP NORTH AMERICA INC","7":"SMART APPAREL (US) INC","8":"SMART APPAREL (US) INC","9":"SMART APPAREL (US) INC","10":" Ezoic - mid_content - mid_content ","11":"SMART APPAREL (US) INC","12":"ERIE INDEMNITY COMPANY","13":"ADAPTIVE SPECTRUM AND SIGNAL ALIGNMENT INC"},"JOB TITLE":{"0":"IT ADMINISTRATOR","1":"IT ADMINISTRATOR","2":"IT ADMINISTRATOR","3":"IT ADMINISTRATOR","4":"IT ADMINISTRATOR","5":"IT ADMINISTRATOR","6":"IT ADMINISTRATOR","7":"IT ADMINISTRATOR","8":"IT ADMINISTRATOR","9":"IT ADMINISTRATOR","10":null,"11":"IT ADMINISTRATOR","12":"IT ADMINISTRATOR","13":"IT ADMINISTRATOR"},"BASE SALARY":{"0":"54,060","1":"46,946","2":"51,500","3":"60,000","4":"62,000","5":"62,000","6":"63,000","7":"74,000","8":"74,000","9":"74,000","10":null,"11":"74,000","12":"75,000","13":"94,744"},"LOCATION":{"0":"CARROLLTON, TX","1":"DALLAS, TX","2":"MIAMI, FL","3":"SAN FRANCISCO, CA","4":"ARLINGTON, VA","5":"ARLINGTON, VA","6":"ALPHARETTA, GA","7":"NEW YORK, NY","8":"FRISCO, TX","9":"NEW YORK, NY","10":null,"11":"FRISCO, TX","12":"ERIE, PA","13":"REDWOOD CITY, CA"},"SUBMIT DATE":{"0":"03\/12\/2015","1":"03\/11\/2015","2":"03\/04\/2015","3":"03\/04\/2015","4":"03\/01\/2015","5":"03\/06\/2015","6":"03\/18\/2015","7":"09\/14\/2015","8":"09\/14\/2015","9":"09\/17\/2015","10":null,"11":"09\/17\/2015","12":"09\/04\/2015","13":"02\/13\/2015"},"START DATE":{"0":"09\/11\/2015","1":"09\/10\/2015","2":"09\/01\/2015","3":"09\/02\/2015","4":"08\/01\/2015","5":"09\/01\/2015","6":"09\/16\/2015","7":"09\/25\/2015","8":"09\/25\/2015","9":"09\/25\/2015","10":null,"11":"09\/25\/2015","12":"01\/09\/2016","13":"08\/01\/2015"}},"6":{"EMPLOYER":{"0":"CTBC BANK CO LTD","1":"DWL INTERNATIONAL TRADING COMPANY","2":"PANDA KITCHEN & BATH EXPO CENTER INC","3":"SUNSET POOL INC","4":"AMERICAN DIRECTIONS RESEARCH GROUP INC","5":"KDDI AMERICA INC","6":"KDDI AMERICA INC","7":"NEWMAN INTERNATIONAL ACADEMY OF ARLINGTON","8":"IIT WORKFORCE LLC","9":"CITY OF EAST POINT","10":" Ezoic - mid_content - mid_content ","11":"EXPEDITE CONSTRUCTION & MANAGEMENT SERVICES INC","12":"INP NORTH AMERICA INC","13":"LEEYO SOFTWARE INC","14":"PRO-TECH DESIGN & MANUFACTURING INC"},"JOB TITLE":{"0":"IT ADMINISTRATOR","1":"IT ADMINISTRATOR","2":"IT ADMINISTRATOR","3":"IT ADMINISTRATOR","4":"IT ADMINISTRATOR","5":"IT ADMINISTRATOR","6":"IT ADMINISTRATOR","7":"IT ADMINISTRATOR","8":"IT ADMINISTRATOR","9":"IT ADMINISTRATOR","10":null,"11":"IT ADMINISTRATOR","12":"IT ADMINISTRATOR","13":"IT ADMINISTRATOR","14":"IT ADMINISTRATOR"},"BASE SALARY":{"0":"52,740","1":"53,600","2":"54,400","3":"64,700","4":"50,000","5":"51,813","6":"51,813","7":"52,478","8":"60,000","9":"60,000","10":null,"11":"65,000","12":"66,000","13":"74,000","14":"80,000"},"LOCATION":{"0":"NEW YORK, NY","1":"LODI, NJ","2":"MIAMI, FL","3":"ARLINGTON, VA","4":"WASHINGTON, DC","5":"COSTA MESA, CA","6":"COSTA MESA, CA","7":"ARLINGTON, TX","8":"ALPHARETTA, GA","9":"EAST POINT, GA","10":null,"11":"NEW YORK, NY","12":"ALPHARETTA, GA","13":"SAN JOSE, CA","14":"SANTA FE SPRINGS, CA"},"SUBMIT DATE":{"0":"05\/07\/2016","1":"03\/09\/2016","2":"07\/22\/2016","3":"07\/25\/2016","4":"03\/04\/2016","5":"05\/08\/2016","6":"09\/12\/2016","7":"06\/03\/2016","8":"03\/19\/2016","9":"03\/09\/2016","10":null,"11":"03\/15\/2016","12":"03\/18\/2016","13":"02\/02\/2016","14":"02\/09\/2016"},"START DATE":{"0":"05\/23\/2016","1":"09\/05\/2016","2":"10\/30\/2016","3":"08\/15\/2016","4":"09\/03\/2016","5":"08\/16\/2016","6":"09\/12\/2016","7":"07\/01\/2016","8":"09\/16\/2016","9":"09\/01\/2016","10":null,"11":"09\/14\/2016","12":"09\/17\/2016","13":"02\/04\/2016","14":"08\/07\/2016"}},"7":{"EMPLOYER":{"0":"JCA INC","1":"JCA INC","2":"PHARMFOODS GROUP OF COMPANIES LLC","3":"HEIGHTS GLOBAL IT SERVICE","4":"NCI GROUP INC","5":"CITY OF EAST POINT","6":"CITY OF EAST POINT","7":"SETTY & ASSOCIATES LTD","8":"SETTY & ASSOCIATES LTD","9":"ARISTOCRAT TECHNOLOGIES INC","10":" Ezoic - mid_content - mid_content ","11":"VIVA RAILINGS LLC","12":"VIVA RAILINGS LLC","13":"SEOUL SHIK POOM INC","14":"SEOUL SHIK POOM INC","15":"ERIE INDEMNITY COMPANY","16":"ERIE INDEMNITY COMPANY","17":"NCI GROUP INC","18":"SEOUL SHIK POOM INC","19":"SEOUL SHIK POOM INC"},"JOB TITLE":{"0":"IT ADMINISTRATOR","1":"IT ADMINISTRATOR","2":"IT ADMINISTRATOR","3":"IT ADMINISTRATOR","4":"IT ADMINISTRATOR","5":"IT ADMINISTRATOR","6":"IT ADMINISTRATOR","7":"IT ADMINISTRATOR","8":"IT ADMINISTRATOR","9":"IT ADMINISTRATOR","10":null,"11":"IT ADMINISTRATOR","12":"IT ADMINISTRATOR","13":"IT ADMINISTRATOR","14":"IT ADMINISTRATOR","15":"IT ADMINISTRATOR","16":"IT ADMINISTRATOR","17":"IT ADMINISTRATOR","18":"IT ADMINISTRATOR","19":"IT ADMINISTRATOR"},"BASE SALARY":{"0":"16,000","1":"16,000","2":"46,363","3":"52,478","4":"61,110","5":"61,200","6":"61,200","7":"61,734","8":"61,734","9":"65,000","10":null,"11":"67,000","12":"67,000","13":"70,000","14":"70,000","15":"75,000","16":"75,000","17":"80,018","18":"80,392","19":"80,392"},"LOCATION":{"0":"SAIPAN, MP","1":"SAIPAN, MP","2":"TAMPA, FL","3":"ARLINGTON, TX","4":"HOUSTON, TX","5":"EAST POINT, GA","6":"EAST POINT, GA","7":"NEW YORK, NY","8":"NEW YORK, NY","9":"LAS VEGAS, NV","10":null,"11":"CARROLLTON, TX","12":"CARROLLTON, TX","13":"ENGLEWOOD, NJ","14":"ENGLEWOOD, NJ","15":"ERIE, PA","16":"ERIE, PA","17":"HOUSTON, TX","18":"ENGLEWOOD, NJ","19":"ENGLEWOOD, NJ"},"SUBMIT DATE":{"0":"01\/12\/2017","1":"06\/05\/2017","2":"03\/16\/2017","3":"02\/02\/2017","4":"06\/02\/2017","5":"03\/15\/2017","6":"03\/06\/2017","7":"03\/14\/2017","8":"03\/14\/2017","9":"03\/16\/2017","10":null,"11":"03\/07\/2017","12":"03\/12\/2017","13":"09\/01\/2017","14":"09\/08\/2017","15":"03\/06\/2017","16":"08\/31\/2017","17":"12\/22\/2017","18":"09\/01\/2017","19":"09\/08\/2017"},"START DATE":{"0":"02\/01\/2017","1":"06\/06\/2017","2":"09\/14\/2017","3":"02\/02\/2017","4":"10\/25\/2017","5":"09\/02\/2017","6":"09\/02\/2017","7":"09\/01\/2017","8":"09\/01\/2017","9":"09\/14\/2017","10":null,"11":"08\/24\/2017","12":"08\/24\/2017","13":"09\/29\/2017","14":"09\/29\/2017","15":"03\/20\/2017","16":"09\/18\/2017","17":"01\/04\/2018","18":"09\/29\/2017","19":"09\/29\/2017"}},"8":{"EMPLOYER":{"0":"PHARMFOOD GROUP OF COMPANIES LLC","1":"UNIVERSAL BUSINESS SOLUTIONS INC","2":"SUNSET POOL MANAGEMENT INC","3":"KDDI AMERICA INC","4":"L & J NEW TECH CORP","5":"SAMJAN GROUP INC","6":"ARISTOCRAT TECHNOLOGIES INC","7":"ERIE INDEMNITY COMPANY","8":"WPT ENTERPRISES INC"},"JOB TITLE":{"0":"IT ADMINISTRATOR","1":"IT ADMINISTRATOR","2":"IT ADMINISTRATOR","3":"IT ADMINISTRATOR","4":"IT ADMINISTRATOR","5":"IT ADMINISTRATOR","6":"IT ADMINISTRATOR","7":"IT ADMINISTRATOR","8":"IT ADMINISTRATOR"},"BASE SALARY":{"0":"63,120","1":"77,300","2":"84,000","3":"55,390","4":"55,806","5":"61,443","6":"65,709","7":"75,000","8":"90,000"},"LOCATION":{"0":"TAMPA, FL","1":"NEW YORK, NY","2":"ARLINGTON, VA","3":"TORRANCE, CA","4":"ROSEMEAD, CA","5":"EAST BRUNSWICK, NJ","6":"LAS VEGAS, NV","7":"ERIE, PA","8":"IRVINE, CA"},"SUBMIT DATE":{"0":"03\/23\/2018","1":"03\/16\/2018","2":"03\/09\/2018","3":"04\/02\/2018","4":"04\/21\/2018","5":"03\/09\/2018","6":"01\/30\/2018","7":"11\/30\/2018","8":"03\/15\/2018"},"START DATE":{"0":"09\/16\/2018","1":"09\/15\/2018","2":"09\/01\/2018","3":"10\/01\/2018","4":"06\/01\/2018","5":"09\/08\/2018","6":"07\/28\/2018","7":"12\/24\/2018","8":"09\/10\/2018"}},"9":{"EMPLOYER":{"0":"HARCO MANUFACTURING GROUP LLC","1":"HARCO MANUFACTURING GROUP LLC","2":"HARCO MANUFACTURING GROUP LLC","3":"ATLANTA COUNTRY SCHOOL INC","4":"KDDI AMERICA INC","5":"GESTAMP CHATTANOOGA LLC","6":"GESTAMP CHATTANOOGA II LLC","7":"BEST FOOD SERVICES INC","8":"ACQUIFIN INC","9":"UDACITY INC"},"JOB TITLE":{"0":"IT ADMINISTRATOR","1":"IT ADMINISTRATOR","2":"IT ADMINISTRATOR","3":"IT ADMINISTRATOR","4":"IT ADMINISTRATOR","5":"IT ADMINISTRATOR","6":"IT ADMINISTRATOR","7":"IT ADMINISTRATOR","8":"IT ADMINISTRATOR","9":"IT ADMINISTRATOR"},"BASE SALARY":{"0":"46,440","1":"46,440","2":"46,440","3":"54,640","4":"59,051","5":"60,000","6":"60,000","7":"61,318","8":"72,966","9":"83,200"},"LOCATION":{"0":"MORAINE, OH","1":"MORAINE, OH","2":"MORAINE, OH","3":"SANDY SPRINGS, GA","4":"TORRANCE, CA","5":"CHATTANOOGA, TN","6":"CHATTANOOGA, TN","7":"CHICAGO, IL","8":"DORAL, FL","9":"SAN FRANCISCO, CA"},"SUBMIT DATE":{"0":"03\/19\/2019","1":"03\/24\/2019","2":"03\/24\/2019","3":"03\/14\/2019","4":"08\/10\/2019","5":"03\/18\/2019","6":"03\/16\/2019","7":"03\/04\/2019","8":"03\/27\/2019","9":"03\/20\/2019"},"START DATE":{"0":"09\/18\/2019","1":"09\/18\/2019","2":"09\/18\/2019","3":"09\/01\/2019","4":"02\/07\/2020","5":"09\/12\/2019","6":"09\/12\/2019","7":"08\/20\/2019","8":"09\/21\/2019","9":"09\/19\/2019"}},"10":{"EMPLOYER":{"0":"G-TECH SERVICES INC","1":"LAKESHORE MANOR LLC","2":"SEOUL SHIK POOM INC","3":"ERIE INDEMNITY COMPANY","4":"CITY OF EAST POINT","5":"SCOPELY INC","6":"HILL TOP RESEARCH INC","7":"SCOPELY INC"},"JOB TITLE":{"0":"IT ADMINISTRATOR","1":"IT ADMINISTRATOR","2":"IT ADMINISTRATOR","3":"IT ADMINISTRATOR","4":"IT ADMINISTRATOR","5":"IT ADMINISTRATOR","6":"IT ADMINISTRATOR","7":"IT ADMINISTRATOR"},"BASE SALARY":{"0":"57,980","1":"67,700","2":"79,380","3":"54,267","4":"65,293","5":"71,157","6":"75,000","7":"77,376"},"LOCATION":{"0":"ALLEN PARK, MI","1":"CLERMONT, FL","2":"ENGLEWOOD, NJ","3":"ERIE, PA","4":"EAST POINT, GA","5":"BOULDER, CO","6":"ST. PETERSBURG, FL","7":"BOULDER, CO"},"SUBMIT DATE":{"0":"06\/11\/2020","1":"02\/27\/2020","2":"07\/01\/2020","3":"06\/02\/2020","4":"02\/19\/2020","5":"02\/28\/2020","6":"04\/23\/2020","7":"03\/16\/2020"},"START DATE":{"0":"10\/01\/2020","1":"08\/25\/2020","2":"09\/28\/2020","3":"06\/08\/2020","4":"08\/20\/2020","5":"03\/16\/2020","6":"10\/01\/2020","7":"03\/23\/2020"}}}}